Candas2/__init__.py
Candas2/candas2.py
candas2-0.0.1.dist-info/LICENSE.txt
candas2-0.0.1.dist-info/METADATA
candas2-0.0.1.dist-info/WHEEL
candas2-0.0.1.dist-info/top_level.txt
candas2-0.0.1.dist-info/RECORD
