Metadata-Version: 2.1
Name: candas2
Version: 0.0.1
Summary: This is a project inspired on the original Candas library by https://gist.github.com/JulianWgs, a blf file can be handle in a faster way using python data science classical libraries.
Home-page: https://github.com/Dr-Br0t/Candas2
Author: Dr-Br0t
Author-email: dr.br00tz@gmail.com
License: GNU Affero General Public License v3
Classifier: Programming Language :: Python :: 3
Classifier: License :: OSI Approved :: GNU Affero General Public License v3
Classifier: Operating System :: OS Independent
License-File: LICENSE.txt
